gym_classics/__init__.py
gym_classics/dynamic_programming.py
gym_classics/utils.py
gym_classics/envs/__init__.py
gym_classics/envs/classic_gridworld.py
gym_classics/envs/cliff_walk.py
gym_classics/envs/dyna_maze.py
gym_classics/envs/four_rooms.py
gym_classics/envs/jacks_car_rental.py
gym_classics/envs/linear_walks.py
gym_classics/envs/racetracks.py
gym_classics/envs/sparse_gridworld.py
gym_classics/envs/windy_gridworld.py
gym_classics/envs/abstract/__init__.py
gym_classics/envs/abstract/base_env.py
gym_classics/envs/abstract/gridworld.py
gym_classics/envs/abstract/linear_walk.py
gym_classics/envs/abstract/noisy_gridworld.py
gym_classics/envs/abstract/racetrack.py
tests/__init__.py
gym_classics-1.0.0.dist-info/LICENSE
gym_classics-1.0.0.dist-info/METADATA
gym_classics-1.0.0.dist-info/WHEEL
gym_classics-1.0.0.dist-info/top_level.txt
gym_classics-1.0.0.dist-info/RECORD
