Metadata-Version: 2.1
Name: gym-classics
Version: 1.0.0
Summary: Classic environments for reinforcement learning and dynamic programming, implemented in OpenAI Gym and Gymnasium.
Home-page: https://github.com/brett-daley/gym-classics
Author: Brett Daley
Author-email: brett.daley@ualberta.ca
Classifier: Programming Language :: Python :: 3
Classifier: License :: OSI Approved :: GNU General Public License v3 (GPLv3)
Classifier: Operating System :: OS Independent
Requires-Python: >=3.5
License-File: LICENSE
